{
  "type": "FeatureCollection",
  "features": [
    {
      "type": "Feature",
      "geometry": {
        "type": "Point",
        "coordinates": [
          18.02,
          27.04
        ]
      },
      "properties": {
        "id": "52241",
        "name": "Libya: Floods - Dec 2024",
        "status": "ongoing",
        "description": "Recent heavy rainfall in Libya has resulted in widespread flooding across several municipalities, impacting communities, infrastructure, and essential services. The most affected areas include Tarhuna, Bani Waleed, Ghiryan, Qasr Akhyar, Ain Zara, Garabolli and Tajoura. Many roads have been rendered impassable, complicating the delivery of aid. The floods have led to five confirmed casualties – three civilians and two rescue workers from the Emergency and Ambulance Service in Tarhuna – and affected around 667 families in various areas. ([OCHA, 11 Dec 2024](https://reliefweb.int/node/4117304))",
        "country": "Libya",
        "createdDate": "2024-12-11T11:21:07+00:00",
        "changedDate": "2024-12-11T12:52:21+00:00"
      }
    }
  ]
}